[{
  "_id": {
    "$oid": "66069ff93007b006635c0245"
  },
  "brandName": "Ward, Hand and Ortiz",
  "yearFounded": 1970,
  "headquarters": "Jastside",
  "numberOfLocations": 2132,
  "createdAt": {
    "$date": "2024-04-20T14:17:10.757Z"
  },
  "updatedAt": {
    "$date": "2024-04-20T14:17:10.757Z"
  },
  "__v": 0
},
{
  "_id": {
    "$oid": "66069ff93007b006635c0246"
  },
  "brandName": "Ergonomic Frozen Bacon",
  "yearFounded": 1600,
  "headquarters": "Gavinstead",
  "numberOfLocations": 1,
  "createdAt": {
    "$date": "2024-04-20T14:17:10.766Z"
  },
  "updatedAt": {
    "$date": "2024-04-20T14:17:10.766Z"
  },
  "__v": 0
},
{
  "_id": {
    "$oid": "66069ff93007b006635c0247"
  },
  "brandName": "Breitenberg, Greenholt and Ledner",
  "yearFounded": 1982,
  "headquarters": "Fort Lenna",
  "numberOfLocations": 1000,
  "createdAt": {
    "$date": "2024-04-20T14:17:10.770Z"
  },
  "updatedAt": {
    "$date": "2024-04-20T14:17:10.770Z"
  },
  "__v": 0
},
{
  "_id": {
    "$oid": "66069ff93007b006635c0248"
  },
  "brandName": "Modern Granite Fish",
  "yearFounded": 1970,
  "headquarters": "Kundebury",
  "numberOfLocations": 1,
  "createdAt": {
    "$date": "2024-04-20T14:17:10.774Z"
  },
  "updatedAt": {
    "$date": "2024-04-20T14:17:10.774Z"
  },
  "__v": 0
},
{
  "_id": {
    "$oid": "66069ff93007b006635c0249"
  },
  "brandName": "Gorgeous Granite Pizza",
  "yearFounded": 1980,
  "headquarters": "Jonesborough",
  "numberOfLocations": 1,
  "createdAt": {
    "$date": "2024-04-20T14:17:10.778Z"
  },
  "updatedAt": {
    "$date": "2024-04-20T14:17:10.778Z"
  },
  "__v": 0
},
{
  "_id": {
    "$oid": "66069ff93007b006635c024a"
  },
  "brandName": "Oriental Plastic Pants",
  "yearFounded": 1970,
  "headquarters": "Wardfort",
  "numberOfLocations": 1,
  "createdAt": {
    "$date": "2024-04-20T14:17:10.781Z"
  },
  "updatedAt": {
    "$date": "2024-04-20T14:17:10.781Z"
  },
  "__v": 0
},
{
  "_id": {
    "$oid": "66069ff93007b006635c024b"
  },
  "brandName": "Refined Granite Towels",
  "yearFounded": 1600,
  "headquarters": "Lemkeland",
  "numberOfLocations": 1,
  "createdAt": {
    "$date": "2024-04-20T14:17:10.784Z"
  },
  "updatedAt": {
    "$date": "2024-04-20T14:17:10.784Z"
  },
  "__v": 0
},
{
  "_id": {
    "$oid": "66069ff93007b006635c024c"
  },
  "brandName": "Corkery Inc",
  "yearFounded": 1935,
  "headquarters": "DuBuqueburgh",
  "numberOfLocations": 9200,
  "createdAt": {
    "$date": "2024-04-20T14:17:10.787Z"
  },
  "updatedAt": {
    "$date": "2024-04-20T14:17:10.787Z"
  },
  "__v": 0
},
{
  "_id": {
    "$oid": "66069ff93007b006635c024d"
  },
  "brandName": "Licensed Concrete Tuna",
  "yearFounded": 1600,
  "headquarters": "West Mylesboro",
  "numberOfLocations": 1,
  "createdAt": {
    "$date": "2024-04-20T14:17:10.791Z"
  },
  "updatedAt": {
    "$date": "2024-04-20T14:17:10.791Z"
  },
  "__v": 0
},
{
  "_id": {
    "$oid": "66069ff93007b006635c024e"
  },
  "brandName": "Generic Cotton Pizza",
  "yearFounded": 1600,
  "headquarters": "North Ralphport",
  "numberOfLocations": 1,
  "createdAt": {
    "$date": "2024-04-20T14:17:10.793Z"
  },
  "updatedAt": {
    "$date": "2024-04-20T14:17:10.793Z"
  },
  "__v": 0
},
{
  "_id": {
    "$oid": "6623ce66b35c80ed3ea23421"
  },
  "brandName": "Intelligent Cotton Chips",
  "yearFounded": 1911,
  "headquarters": "East Grayce",
  "numberOfLocations": 1242,
  "createdAt": {
    "$date": "2024-04-20T14:17:10.820Z"
  },
  "updatedAt": {
    "$date": "2024-04-20T14:17:10.820Z"
  },
  "__v": 0
},
{
  "_id": {
    "$oid": "6623ce66b35c80ed3ea23423"
  },
  "brandName": "Modern Plastic Chair",
  "yearFounded": 1791,
  "headquarters": "Fort Kyleigh",
  "numberOfLocations": 7898,
  "createdAt": {
    "$date": "2024-04-20T14:17:10.825Z"
  },
  "updatedAt": {
    "$date": "2024-04-20T14:17:10.825Z"
  },
  "__v": 0
},
{
  "_id": {
    "$oid": "6623ce66b35c80ed3ea23425"
  },
  "brandName": "Handmade Steel Gloves",
  "yearFounded": 1898,
  "headquarters": "Luzberg",
  "numberOfLocations": 8095,
  "createdAt": {
    "$date": "2024-04-20T14:17:10.827Z"
  },
  "updatedAt": {
    "$date": "2024-04-20T14:17:10.827Z"
  },
  "__v": 0
},
{
  "_id": {
    "$oid": "6623ce66b35c80ed3ea23427"
  },
  "brandName": "Elegant Concrete Towels",
  "yearFounded": 1810,
  "headquarters": "Kaceystad",
  "numberOfLocations": 5851,
  "createdAt": {
    "$date": "2024-04-20T14:17:10.829Z"
  },
  "updatedAt": {
    "$date": "2024-04-20T14:17:10.829Z"
  },
  "__v": 0
},
{
  "_id": {
    "$oid": "6623ce66b35c80ed3ea23429"
  },
  "brandName": "Recycled Metal Ball",
  "yearFounded": 1943,
  "headquarters": "Hammesburgh",
  "numberOfLocations": 8634,
  "createdAt": {
    "$date": "2024-04-20T14:17:10.830Z"
  },
  "updatedAt": {
    "$date": "2024-04-20T14:17:10.830Z"
  },
  "__v": 0
},
{
  "_id": {
    "$oid": "6623ce66b35c80ed3ea2342b"
  },
  "brandName": "Oriental Fresh Mouse",
  "yearFounded": 1956,
  "headquarters": "Boganborough",
  "numberOfLocations": 4188,
  "createdAt": {
    "$date": "2024-04-20T14:17:10.832Z"
  },
  "updatedAt": {
    "$date": "2024-04-20T14:17:10.832Z"
  },
  "__v": 0
},
{
  "_id": {
    "$oid": "6623ce66b35c80ed3ea2342d"
  },
  "brandName": "Bespoke Steel Cheese",
  "yearFounded": 1996,
  "headquarters": "Marquardtboro",
  "numberOfLocations": 6041,
  "createdAt": {
    "$date": "2024-04-20T14:17:10.834Z"
  },
  "updatedAt": {
    "$date": "2024-04-20T14:17:10.834Z"
  },
  "__v": 0
},
{
  "_id": {
    "$oid": "6623ce66b35c80ed3ea2342f"
  },
  "brandName": "Ergonomic Plastic Pizza",
  "yearFounded": 2004,
  "headquarters": "Rockwall",
  "numberOfLocations": 4708,
  "createdAt": {
    "$date": "2024-04-20T14:17:10.836Z"
  },
  "updatedAt": {
    "$date": "2024-04-20T14:17:10.836Z"
  },
  "__v": 0
},
{
  "_id": {
    "$oid": "6623ce66b35c80ed3ea23431"
  },
  "brandName": "Small Frozen Soap",
  "yearFounded": 1772,
  "headquarters": "Port Trever",
  "numberOfLocations": 1450,
  "createdAt": {
    "$date": "2024-04-20T14:17:10.838Z"
  },
  "updatedAt": {
    "$date": "2024-04-20T14:17:10.838Z"
  },
  "__v": 0
},
{
  "_id": {
    "$oid": "6623ce66b35c80ed3ea23433"
  },
  "brandName": "Refined Metal Sausages",
  "yearFounded": 1768,
  "headquarters": "Howellbury",
  "numberOfLocations": 652,
  "createdAt": {
    "$date": "2024-04-20T14:17:10.839Z"
  },
  "updatedAt": {
    "$date": "2024-04-20T14:17:10.839Z"
  },
  "__v": 0
}]